[
  {
    "id": 0,
    "text": " Kopfschmerzen, Bauchschmerzen und ihr ist übel.",
    "start": 1.296,
    "end": 4.378,
    "words": [
      {
        "text": "Kopfschmerzen,",
        "start": 1.296,
        "end": 2.137
      },
      {
        "text": "Bauchschmerzen",
        "start": 2.157,
        "end": 3.057
      },
      {
        "text": "und",
        "start": 3.097,
        "end": 3.277
      },
      {
        "text": "ihr",
        "start": 3.317,
        "end": 3.377
      },
      {
        "text": "ist",
        "start": 3.417,
        "end": 3.657
      },
      {
        "text": "übel.",
        "start": 3.717,
        "end": 4.378
      }
    ]
  },
  {
    "id": 1,
    "text": "Ob sie jemand vergiften will?",
    "start": 4.438,
    "end": 6.519,
    "words": [
      {
        "text": "Ob",
        "start": 4.438,
        "end": 4.598
      },
      {
        "text": "sie",
        "start": 4.638,
        "end": 4.798
      },
      {
        "text": "jemand",
        "start": 4.818,
        "end": 5.158
      },
      {
        "text": "vergiften",
        "start": 5.178,
        "end": 5.678
      },
      {
        "text": "will?",
        "start": 5.718,
        "end": 6.519
      }
    ]
  },
  {
    "id": 2,
    "text": "Ach was, ein Thronstreit wäre noch lange kein Grund, ihr nach dem Leben zu trachten.",
    "start": 6.599,
    "end": 10.901,
    "words": [
      {
        "text": "Ach",
        "start": 6.599,
        "end": 6.819
      },
      {
        "text": "was,",
        "start": 6.879,
        "end": 7.059
      },
      {
        "text": "ein",
        "start": 7.159,
        "end": 7.359
      },
      {
        "text": "Thronstreit",
        "start": 7.379,
        "end": 7.92
      },
      {
        "text": "wäre",
        "start": 7.94,
        "end": 8.16
      },
      {
        "text": "noch",
        "start": 8.18,
        "end": 8.32
      },
      {
        "text": "lange",
        "start": 8.36,
        "end": 8.6
      },
      {
        "text": "kein",
        "start": 8.62,
        "end": 8.78
      },
      {
        "text": "Grund,",
        "start": 8.8,
        "end": 8.94
      },
      {
        "text": "ihr",
        "start": 8.98,
        "end": 9.08
      },
      {
        "text": "nach",
        "start": 9.12,
        "end": 9.24
      },
      {
        "text": "dem",
        "start": 9.26,
        "end": 9.4
      },
      {
        "text": "Leben",
        "start": 9.42,
        "end": 9.7
      },
      {
        "text": "zu",
        "start": 9.74,
        "end": 9.841
      },
      {
        "text": "trachten.",
        "start": 9.881,
        "end": 10.901
      }
    ]
  },
  {
    "id": 3,
    "text": "Also scheidet Gift schon mal aus, bleibt nur noch... eine Krankheit vielleicht.",
    "start": 10.961,
    "end": 17.144,
    "words": [
      {
        "text": "Also",
        "start": 10.961,
        "end": 11.181
      },
      {
        "text": "scheidet",
        "start": 11.221,
        "end": 11.541
      },
      {
        "text": "Gift",
        "start": 11.561,
        "end": 11.742
      },
      {
        "text": "schon",
        "start": 11.762,
        "end": 11.902
      },
      {
        "text": "mal",
        "start": 12.002,
        "end": 12.142
      },
      {
        "text": "aus,",
        "start": 12.182,
        "end": 12.402
      },
      {
        "text": "bleibt",
        "start": 12.442,
        "end": 12.762
      },
      {
        "text": "nur",
        "start": 12.782,
        "end": 12.942
      },
      {
        "text": "noch...",
        "start": 12.982,
        "end": 13.863
      },
      {
        "text": "eine",
        "start": 13.903,
        "end": 14.143
      },
      {
        "text": "Krankheit",
        "start": 14.183,
        "end": 14.723
      },
      {
        "text": "vielleicht.",
        "start": 14.763,
        "end": 17.144
      }
    ]
  },
  {
    "id": 4,
    "text": "Oder es hat etwas mit der Blutlinie zu tun.",
    "start": 17.224,
    "end": 21.326,
    "words": [
      {
        "text": "Oder",
        "start": 17.224,
        "end": 17.444
      },
      {
        "text": "es",
        "start": 17.504,
        "end": 17.585
      },
      {
        "text": "hat",
        "start": 17.625,
        "end": 17.785
      },
      {
        "text": "etwas",
        "start": 17.825,
        "end": 18.045
      },
      {
        "text": "mit",
        "start": 18.065,
        "end": 18.165
      },
      {
        "text": "der",
        "start": 18.205,
        "end": 18.305
      },
      {
        "text": "Blutlinie",
        "start": 18.325,
        "end": 18.905
      },
      {
        "text": "zu",
        "start": 18.945,
        "end": 19.065
      },
      {
        "text": "tun.",
        "start": 19.105,
        "end": 21.326
      }
    ]
  },
  {
    "id": 5,
    "text": "Ich sollte so ein dämliches Gerücht überhaupt nicht ernst nehmen.",
    "start": 21.386,
    "end": 25.909,
    "words": [
      {
        "text": "Ich",
        "start": 21.386,
        "end": 21.547
      },
      {
        "text": "sollte",
        "start": 21.587,
        "end": 21.927
      },
      {
        "text": "so",
        "start": 21.947,
        "end": 22.087
      },
      {
        "text": "ein",
        "start": 22.107,
        "end": 22.207
      },
      {
        "text": "dämliches",
        "start": 22.247,
        "end": 22.727
      },
      {
        "text": "Gerücht",
        "start": 22.767,
        "end": 23.127
      },
      {
        "text": "überhaupt",
        "start": 23.167,
        "end": 23.528
      },
      {
        "text": "nicht",
        "start": 23.548,
        "end": 23.788
      },
      {
        "text": "ernst",
        "start": 23.828,
        "end": 24.128
      },
      {
        "text": "nehmen.",
        "start": 24.188,
        "end": 25.909
      }
    ]
  },
  {
    "id": 6,
    "text": "Es gibt doch nicht einen einzigen Beweis dafür.",
    "start": 25.969,
    "end": 28.03,
    "words": [
      {
        "text": "Es",
        "start": 25.969,
        "end": 26.069
      },
      {
        "text": "gibt",
        "start": 26.109,
        "end": 26.249
      },
      {
        "text": "doch",
        "start": 26.289,
        "end": 26.429
      },
      {
        "text": "nicht",
        "start": 26.449,
        "end": 26.669
      },
      {
        "text": "einen",
        "start": 26.689,
        "end": 26.869
      },
      {
        "text": "einzigen",
        "start": 26.909,
        "end": 27.309
      },
      {
        "text": "Beweis",
        "start": 27.349,
        "end": 27.73
      },
      {
        "text": "dafür.",
        "start": 27.75,
        "end": 28.03
      }
    ]
  },
  {
    "id": 7,
    "text": " Allerdings... Könnte ich mir das mal genauer ansehen.",
    "start": 29.956,
    "end": 34.539,
    "words": [
      {
        "text": "Allerdings...",
        "start": 29.956,
        "end": 32.758
      },
      {
        "text": "Könnte",
        "start": 32.778,
        "end": 33.038
      },
      {
        "text": "ich",
        "start": 33.078,
        "end": 33.178
      },
      {
        "text": "mir",
        "start": 33.198,
        "end": 33.318
      },
      {
        "text": "das",
        "start": 33.358,
        "end": 33.458
      },
      {
        "text": "mal",
        "start": 33.538,
        "end": 33.679
      },
      {
        "text": "genauer",
        "start": 33.719,
        "end": 34.099
      },
      {
        "text": "ansehen.",
        "start": 34.139,
        "end": 34.539
      }
    ]
  },
  {
    "id": 8,
    "text": "Oh ja, der Plan gefällt mir.",
    "start": 34.979,
    "end": 40.002,
    "words": [
      {
        "text": "Oh",
        "start": 34.979,
        "end": 35.119
      },
      {
        "text": "ja,",
        "start": 35.159,
        "end": 35.32
      },
      {
        "text": "der",
        "start": 35.34,
        "end": 35.52
      },
      {
        "text": "Plan",
        "start": 35.54,
        "end": 35.78
      },
      {
        "text": "gefällt",
        "start": 35.8,
        "end": 36.22
      },
      {
        "text": "mir.",
        "start": 36.24,
        "end": 40.002
      }
    ]
  },
  {
    "id": 9,
    "text": "Jetzt, wo ich hier bei den Residenzen der erstrangigen Gemahlinnen stehe, fällt mir auf, dass selbst die Pfeiler eleganter aussehen als bei uns.",
    "start": 40.043,
    "end": 46.987,
    "words": [
      {
        "text": "Jetzt,",
        "start": 40.043,
        "end": 40.283
      },
      {
        "text": "wo",
        "start": 40.303,
        "end": 40.443
      },
      {
        "text": "ich",
        "start": 40.463,
        "end": 40.583
      },
      {
        "text": "hier",
        "start": 40.603,
        "end": 40.763
      },
      {
        "text": "bei",
        "start": 40.803,
        "end": 40.903
      },
      {
        "text": "den",
        "start": 40.923,
        "end": 41.083
      },
      {
        "text": "Residenzen",
        "start": 41.123,
        "end": 41.744
      },
      {
        "text": "der",
        "start": 41.784,
        "end": 41.884
      },
      {
        "text": "erstrangigen",
        "start": 41.924,
        "end": 42.504
      },
      {
        "text": "Gemahlinnen",
        "start": 42.544,
        "end": 43.124
      },
      {
        "text": "stehe,",
        "start": 43.164,
        "end": 43.885
      },
      {
        "text": "fällt",
        "start": 43.925,
        "end": 44.165
      },
      {
        "text": "mir",
        "start": 44.205,
        "end": 44.345
      },
      {
        "text": "auf,",
        "start": 44.365,
        "end": 44.485
      },
      {
        "text": "dass",
        "start": 44.525,
        "end": 44.685
      },
      {
        "text": "selbst",
        "start": 44.725,
        "end": 44.926
      },
      {
        "text": "die",
        "start": 44.966,
        "end": 45.106
      },
      {
        "text": "Pfeiler",
        "start": 45.126,
        "end": 45.446
      },
      {
        "text": "eleganter",
        "start": 45.486,
        "end": 45.966
      },
      {
        "text": "aussehen",
        "start": 46.006,
        "end": 46.386
      },
      {
        "text": "als",
        "start": 46.426,
        "end": 46.607
      },
      {
        "text": "bei",
        "start": 46.647,
        "end": 46.827
      },
      {
        "text": "uns.",
        "start": 46.867,
        "end": 46.987
      }
    ]
  },
  {
    "id": 10,
    "text": " Ich weiß, dass ihr's wart!",
    "start": 50.518,
    "end": 51.479,
    "words": [
      {
        "text": "Ich",
        "start": 50.518,
        "end": 50.598
      },
      {
        "text": "weiß,",
        "start": 50.638,
        "end": 50.818
      },
      {
        "text": "dass",
        "start": 50.838,
        "end": 51.038
      },
      {
        "text": "ihr's",
        "start": 51.078,
        "end": 51.239
      },
      {
        "text": "wart!",
        "start": 51.279,
        "end": 51.479
      }
    ]
  },
  {
    "id": 11,
    "text": "Verehrte Gyokuyo!",
    "start": 51.879,
    "end": 53.32,
    "words": [
      {
        "text": "Verehrte",
        "start": 51.879,
        "end": 52.279
      },
      {
        "text": "Gyokuyo!",
        "start": 52.319,
        "end": 53.32
      }
    ]
  },
  {
    "id": 12,
    "text": "Und das nur, weil ihr eine Tochter geboren habt!",
    "start": 53.4,
    "end": 55.581,
    "words": [
      {
        "text": "Und",
        "start": 53.4,
        "end": 53.54
      },
      {
        "text": "das",
        "start": 53.56,
        "end": 53.78
      },
      {
        "text": "nur,",
        "start": 53.8,
        "end": 53.96
      },
      {
        "text": "weil",
        "start": 53.98,
        "end": 54.1
      },
      {
        "text": "ihr",
        "start": 54.14,
        "end": 54.24
      },
      {
        "text": "eine",
        "start": 54.261,
        "end": 54.421
      },
      {
        "text": "Tochter",
        "start": 54.461,
        "end": 54.801
      },
      {
        "text": "geboren",
        "start": 54.841,
        "end": 55.201
      },
      {
        "text": "habt!",
        "start": 55.241,
        "end": 55.581
      }
    ]
  },
  {
    "id": 13,
    "text": "Und jetzt wollt ihr meinen Sohn mit einem Fluch umbringen!",
    "start": 55.601,
    "end": 57.963,
    "words": [
      {
        "text": "Und",
        "start": 55.601,
        "end": 55.761
      },
      {
        "text": "jetzt",
        "start": 55.801,
        "end": 55.942
      },
      {
        "text": "wollt",
        "start": 55.982,
        "end": 56.142
      },
      {
        "text": "ihr",
        "start": 56.202,
        "end": 56.282
      },
      {
        "text": "meinen",
        "start": 56.302,
        "end": 56.482
      },
      {
        "text": "Sohn",
        "start": 56.522,
        "end": 56.722
      },
      {
        "text": "mit",
        "start": 56.762,
        "end": 56.862
      },
      {
        "text": "einem",
        "start": 56.882,
        "end": 57.042
      },
      {
        "text": "Fluch",
        "start": 57.082,
        "end": 57.403
      },
      {
        "text": "umbringen!",
        "start": 57.443,
        "end": 57.963
      }
    ]
  },
  {
    "id": 14,
    "text": "Ihr wisst ganz genau, dass das nicht der Wahrheit entspricht!",
    "start": 58.023,
    "end": 61.105,
    "words": [
      {
        "text": "Ihr",
        "start": 58.023,
        "end": 58.203
      },
      {
        "text": "wisst",
        "start": 58.243,
        "end": 58.503
      },
      {
        "text": "ganz",
        "start": 58.543,
        "end": 58.803
      },
      {
        "text": "genau,",
        "start": 58.843,
        "end": 59.124
      },
      {
        "text": "dass",
        "start": 59.144,
        "end": 59.324
      },
      {
        "text": "das",
        "start": 59.364,
        "end": 59.524
      },
      {
        "text": "nicht",
        "start": 59.564,
        "end": 59.724
      },
      {
        "text": "der",
        "start": 59.764,
        "end": 59.884
      },
      {
        "text": "Wahrheit",
        "start": 59.904,
        "end": 60.224
      },
      {
        "text": "entspricht!",
        "start": 60.264,
        "end": 61.105
      }
    ]
  },
  {
    "id": 15,
    "text": "Meine kleine Shaolin leidet genauso wie euer Sohn!",
    "start": 61.145,
    "end": 64.327,
    "words": [
      {
        "text": "Meine",
        "start": 61.145,
        "end": 61.385
      },
      {
        "text": "kleine",
        "start": 61.425,
        "end": 61.685
      },
      {
        "text": "Shaolin",
        "start": 61.725,
        "end": 62.186
      },
      {
        "text": "leidet",
        "start": 62.226,
        "end": 62.566
      },
      {
        "text": "genauso",
        "start": 62.606,
        "end": 63.006
      },
      {
        "text": "wie",
        "start": 63.026,
        "end": 63.126
      },
      {
        "text": "euer",
        "start": 63.166,
        "end": 63.446
      },
      {
        "text": "Sohn!",
        "start": 63.486,
        "end": 64.327
      }
    ]
  },
  {
    "id": 16,
    "text": "So aufgebracht habe ich die verehrte Rifa noch nie gesehen.",
    "start": 64.347,
    "end": 66.768,
    "words": [
      {
        "text": "So",
        "start": 64.347,
        "end": 64.587
      },
      {
        "text": "aufgebracht",
        "start": 64.607,
        "end": 65.127
      },
      {
        "text": "habe",
        "start": 65.167,
        "end": 65.268
      },
      {
        "text": "ich",
        "start": 65.308,
        "end": 65.408
      },
      {
        "text": "die",
        "start": 65.428,
        "end": 65.508
      },
      {
        "text": "verehrte",
        "start": 65.528,
        "end": 65.848
      },
      {
        "text": "Rifa",
        "start": 65.908,
        "end": 66.148
      },
      {
        "text": "noch",
        "start": 66.188,
        "end": 66.328
      },
      {
        "text": "nie",
        "start": 66.348,
        "end": 66.468
      },
      {
        "text": "gesehen.",
        "start": 66.488,
        "end": 66.768
      }
    ]
  },
  {
    "id": 17,
    "text": "Die verehrte Gyokuyo kann einem leidtun.",
    "start": 67.129,
    "end": 69.21,
    "words": [
      {
        "text": "Die",
        "start": 67.129,
        "end": 67.229
      },
      {
        "text": "verehrte",
        "start": 67.249,
        "end": 67.609
      },
      {
        "text": "Gyokuyo",
        "start": 67.649,
        "end": 68.129
      },
      {
        "text": "kann",
        "start": 68.149,
        "end": 68.269
      },
      {
        "text": "einem",
        "start": 68.309,
        "end": 68.51
      },
      {
        "text": "leidtun.",
        "start": 68.55,
        "end": 69.21
      }
    ]
  },
  {
    "id": 18,
    "text": "Eure Exzellenz.",
    "start": 69.27,
    "end": 70.151,
    "words": [
      {
        "text": "Eure",
        "start": 69.27,
        "end": 69.55
      },
      {
        "text": "Exzellenz.",
        "start": 69.59,
        "end": 70.151
      }
    ]
  },
  {
    "id": 19,
    "text": " Und deswegen bin ich hier.",
    "start": 73.402,
    "end": 74.623,
    "words": [
      {
        "text": "Und",
        "start": 73.402,
        "end": 73.602
      },
      {
        "text": "deswegen",
        "start": 73.622,
        "end": 73.983
      },
      {
        "text": "bin",
        "start": 74.023,
        "end": 74.143
      },
      {
        "text": "ich",
        "start": 74.183,
        "end": 74.323
      },
      {
        "text": "hier.",
        "start": 74.363,
        "end": 74.623
      }
    ]
  },
  {
    "id": 20,
    "text": "Ich wünsche, dass der Arzt sich meine Tochter ansieht.",
    "start": 74.663,
    "end": 76.665,
    "words": [
      {
        "text": "Ich",
        "start": 74.663,
        "end": 74.743
      },
      {
        "text": "wünsche,",
        "start": 74.784,
        "end": 75.044
      },
      {
        "text": "dass",
        "start": 75.064,
        "end": 75.224
      },
      {
        "text": "der",
        "start": 75.264,
        "end": 75.344
      },
      {
        "text": "Arzt",
        "start": 75.364,
        "end": 75.564
      },
      {
        "text": "sich",
        "start": 75.604,
        "end": 75.764
      },
      {
        "text": "meine",
        "start": 75.805,
        "end": 75.985
      },
      {
        "text": "Tochter",
        "start": 76.025,
        "end": 76.285
      },
      {
        "text": "ansieht.",
        "start": 76.325,
        "end": 76.665
      }
    ]
  },
  {
    "id": 21,
    "text": "Ja, aber ich muss doch... Also... Der panische Oinouch soll der Hofarzt sein?",
    "start": 77.126,
    "end": 82.311,
    "words": [
      {
        "text": "Ja,",
        "start": 77.126,
        "end": 77.346
      },
      {
        "text": "aber",
        "start": 77.386,
        "end": 77.606
      },
      {
        "text": "ich",
        "start": 77.646,
        "end": 77.726
      },
      {
        "text": "muss",
        "start": 77.767,
        "end": 77.967
      },
      {
        "text": "doch...",
        "start": 78.007,
        "end": 78.707
      },
      {
        "text": "Also...",
        "start": 78.768,
        "end": 79.708
      },
      {
        "text": "Der",
        "start": 79.769,
        "end": 79.989
      },
      {
        "text": "panische",
        "start": 80.009,
        "end": 80.449
      },
      {
        "text": "Oinouch",
        "start": 80.489,
        "end": 80.87
      },
      {
        "text": "soll",
        "start": 80.91,
        "end": 81.07
      },
      {
        "text": "der",
        "start": 81.11,
        "end": 81.25
      },
      {
        "text": "Hofarzt",
        "start": 81.27,
        "end": 81.831
      },
      {
        "text": "sein?",
        "start": 81.851,
        "end": 82.311
      }
    ]
  },
  {
    "id": 22,
    "text": "Dem steht ja schon Quacksalbe auf die Stirn geschrieben.",
    "start": 82.351,
    "end": 85.554,
    "words": [
      {
        "text": "Dem",
        "start": 82.351,
        "end": 82.511
      },
      {
        "text": "steht",
        "start": 82.551,
        "end": 82.732
      },
      {
        "text": "ja",
        "start": 82.772,
        "end": 82.892
      },
      {
        "text": "schon",
        "start": 82.912,
        "end": 83.072
      },
      {
        "text": "Quacksalbe",
        "start": 83.112,
        "end": 83.653
      },
      {
        "text": "auf",
        "start": 83.693,
        "end": 83.793
      },
      {
        "text": "die",
        "start": 83.813,
        "end": 83.893
      },
      {
        "text": "Stirn",
        "start": 83.933,
        "end": 84.233
      },
      {
        "text": "geschrieben.",
        "start": 84.273,
        "end": 85.554
      }
    ]
  },
  {
    "id": 23,
    "text": "Da steht er so nah neben den beiden Gemahlinnen und es fällt ihm trotzdem nicht auf?",
    "start": 85.614,
    "end": 89.538,
    "words": [
      {
        "text": "Da",
        "start": 85.614,
        "end": 85.775
      },
      {
        "text": "steht",
        "start": 85.815,
        "end": 86.075
      },
      {
        "text": "er",
        "start": 86.115,
        "end": 86.275
      },
      {
        "text": "so",
        "start": 86.295,
        "end": 86.495
      },
      {
        "text": "nah",
        "start": 86.555,
        "end": 86.716
      },
      {
        "text": "neben",
        "start": 86.736,
        "end": 86.996
      },
      {
        "text": "den",
        "start": 87.036,
        "end": 87.176
      },
      {
        "text": "beiden",
        "start": 87.216,
        "end": 87.476
      },
      {
        "text": "Gemahlinnen",
        "start": 87.496,
        "end": 88.077
      },
      {
        "text": "und",
        "start": 88.117,
        "end": 88.217
      },
      {
        "text": "es",
        "start": 88.277,
        "end": 88.357
      },
      {
        "text": "fällt",
        "start": 88.397,
        "end": 88.557
      },
      {
        "text": "ihm",
        "start": 88.598,
        "end": 88.758
      },
      {
        "text": "trotzdem",
        "start": 88.778,
        "end": 89.138
      },
      {
        "text": "nicht",
        "start": 89.178,
        "end": 89.378
      },
      {
        "text": "auf?",
        "start": 89.438,
        "end": 89.538
      }
    ]
  },
  {
    "id": 24,
    "text": " Moment.",
    "start": 90.539,
    "end": 91.339,
    "words": [
      {
        "text": "Moment.",
        "start": 90.539,
        "end": 91.339
      }
    ]
  },
  {
    "id": 25,
    "text": "Oder hat er etwa gar keine Ahnung?",
    "start": 91.399,
    "end": 94.06,
    "words": [
      {
        "text": "Oder",
        "start": 91.399,
        "end": 91.579
      },
      {
        "text": "hat",
        "start": 91.619,
        "end": 91.719
      },
      {
        "text": "er",
        "start": 91.759,
        "end": 91.859
      },
      {
        "text": "etwa",
        "start": 91.899,
        "end": 92.119
      },
      {
        "text": "gar",
        "start": 92.159,
        "end": 92.38
      },
      {
        "text": "keine",
        "start": 92.4,
        "end": 92.72
      },
      {
        "text": "Ahnung?",
        "start": 92.78,
        "end": 94.06
      }
    ]
  },
  {
    "id": 26,
    "text": "Der Tod der Säuglinge, die Kopf- und Bauchschmerzen sowie die Übelkeit.",
    "start": 94.1,
    "end": 98.161,
    "words": [
      {
        "text": "Der",
        "start": 94.1,
        "end": 94.26
      },
      {
        "text": "Tod",
        "start": 94.3,
        "end": 94.52
      },
      {
        "text": "der",
        "start": 94.56,
        "end": 94.7
      },
      {
        "text": "Säuglinge,",
        "start": 94.74,
        "end": 95.3
      },
      {
        "text": "die",
        "start": 95.34,
        "end": 95.46
      },
      {
        "text": "Kopf-",
        "start": 95.48,
        "end": 95.68
      },
      {
        "text": "und",
        "start": 95.74,
        "end": 95.88
      },
      {
        "text": "Bauchschmerzen",
        "start": 95.92,
        "end": 96.641
      },
      {
        "text": "sowie",
        "start": 96.661,
        "end": 96.901
      },
      {
        "text": "die",
        "start": 96.921,
        "end": 97.041
      },
      {
        "text": "Übelkeit.",
        "start": 97.081,
        "end": 98.161
      }
    ]
  },
  {
    "id": 27,
    "text": "Man sieht doch sofort, dass die verehrte Rifa sehr abgemagert ist.",
    "start": 98.201,
    "end": 101.382,
    "words": [
      {
        "text": "Man",
        "start": 98.201,
        "end": 98.421
      },
      {
        "text": "sieht",
        "start": 98.461,
        "end": 98.601
      },
      {
        "text": "doch",
        "start": 98.641,
        "end": 98.801
      },
      {
        "text": "sofort,",
        "start": 98.841,
        "end": 99.221
      },
      {
        "text": "dass",
        "start": 99.261,
        "end": 99.481
      },
      {
        "text": "die",
        "start": 99.521,
        "end": 99.601
      },
      {
        "text": "verehrte",
        "start": 99.641,
        "end": 100.001
      },
      {
        "text": "Rifa",
        "start": 100.021,
        "end": 100.361
      },
      {
        "text": "sehr",
        "start": 100.381,
        "end": 100.541
      },
      {
        "text": "abgemagert",
        "start": 100.561,
        "end": 101.182
      },
      {
        "text": "ist.",
        "start": 101.242,
        "end": 101.382
      }
    ]
  },
  {
    "id": 28,
    "text": "Ich hab es gewusst.",
    "start": 102.062,
    "end": 103.422,
    "words": [
      {
        "text": "Ich",
        "start": 102.062,
        "end": 102.302
      },
      {
        "text": "hab",
        "start": 102.322,
        "end": 102.402
      },
      {
        "text": "es",
        "start": 102.422,
        "end": 102.562
      },
      {
        "text": "gewusst.",
        "start": 102.602,
        "end": 103.422
      }
    ]
  },
  {
    "id": 29,
    "text": "Das ist überhaupt kein Fluch.",
    "start": 103.462,
    "end": 105.243,
    "words": [
      {
        "text": "Das",
        "start": 103.462,
        "end": 103.642
      },
      {
        "text": "ist",
        "start": 103.682,
        "end": 103.882
      },
      {
        "text": "überhaupt",
        "start": 103.902,
        "end": 104.222
      },
      {
        "text": "kein",
        "start": 104.262,
        "end": 104.462
      },
      {
        "text": "Fluch.",
        "start": 104.502,
        "end": 105.243
      }
    ]
  },
  {
    "id": 30,
    "text": "Doch wie soll ich es ihnen mitteilen?",
    "start": 105.303,
    "end": 109.023,
    "words": [
      {
        "text": "Doch",
        "start": 105.303,
        "end": 105.563
      },
      {
        "text": "wie",
        "start": 105.603,
        "end": 105.763
      },
      {
        "text": "soll",
        "start": 105.783,
        "end": 105.983
      },
      {
        "text": "ich",
        "start": 106.003,
        "end": 106.123
      },
      {
        "text": "es",
        "start": 106.163,
        "end": 106.343
      },
      {
        "text": "ihnen",
        "start": 106.383,
        "end": 106.643
      },
      {
        "text": "mitteilen?",
        "start": 106.663,
        "end": 109.023
      }
    ]
  },
  {
    "id": 31,
    "text": "Ich bräuchte etwas, auf dem ich schreiben kann.",
    "start": 109.083,
    "end": 111.384,
    "words": [
      {
        "text": "Ich",
        "start": 109.083,
        "end": 109.303
      },
      {
        "text": "bräuchte",
        "start": 109.323,
        "end": 110.004
      },
      {
        "text": "etwas,",
        "start": 110.044,
        "end": 110.264
      },
      {
        "text": "auf",
        "start": 110.324,
        "end": 110.424
      },
      {
        "text": "dem",
        "start": 110.464,
        "end": 110.564
      },
      {
        "text": "ich",
        "start": 110.624,
        "end": 110.724
      },
      {
        "text": "schreiben",
        "start": 110.744,
        "end": 111.164
      },
      {
        "text": "kann.",
        "start": 111.204,
        "end": 111.384
      }
    ]
  }
]