[
  {
    "id": 0,
    "text": " Moment mal, sag bloß, du hast Trash Chronicles schon durch.",
    "start": 0.031,
    "end": 3.332,
    "words": [
      {
        "text": "Moment",
        "start": 0.031,
        "end": 0.571
      },
      {
        "text": "mal,",
        "start": 0.631,
        "end": 0.851
      },
      {
        "text": "sag",
        "start": 1.232,
        "end": 1.392
      },
      {
        "text": "bloß,",
        "start": 1.432,
        "end": 1.692
      },
      {
        "text": "du",
        "start": 1.712,
        "end": 1.812
      },
      {
        "text": "hast",
        "start": 1.832,
        "end": 1.992
      },
      {
        "text": "Trash",
        "start": 2.012,
        "end": 2.252
      },
      {
        "text": "Chronicles",
        "start": 2.272,
        "end": 2.732
      },
      {
        "text": "schon",
        "start": 2.752,
        "end": 2.972
      },
      {
        "text": "durch.",
        "start": 3.032,
        "end": 3.332
      }
    ]
  },
  {
    "id": 1,
    "text": "Na klar, sonst würde ich doch kein neues anfangen.",
    "start": 4.233,
    "end": 7.054,
    "words": [
      {
        "text": "Na",
        "start": 4.233,
        "end": 4.473
      },
      {
        "text": "klar,",
        "start": 4.513,
        "end": 5.013
      },
      {
        "text": "sonst",
        "start": 5.033,
        "end": 5.233
      },
      {
        "text": "würde",
        "start": 5.273,
        "end": 5.433
      },
      {
        "text": "ich",
        "start": 5.453,
        "end": 5.553
      },
      {
        "text": "doch",
        "start": 5.593,
        "end": 5.774
      },
      {
        "text": "kein",
        "start": 5.794,
        "end": 5.974
      },
      {
        "text": "neues",
        "start": 5.994,
        "end": 6.274
      },
      {
        "text": "anfangen.",
        "start": 6.334,
        "end": 7.054
      }
    ]
  },
  {
    "id": 2,
    "text": "Und, wie fandest du's?",
    "start": 7.134,
    "end": 8.495,
    "words": [
      {
        "text": "Und,",
        "start": 7.134,
        "end": 7.354
      },
      {
        "text": "wie",
        "start": 7.374,
        "end": 7.494
      },
      {
        "text": "fandest",
        "start": 7.514,
        "end": 7.934
      },
      {
        "text": "du's?",
        "start": 7.954,
        "end": 8.495
      }
    ]
  },
  {
    "id": 3,
    "text": "Der absolute Supermüll!",
    "start": 8.535,
    "end": 11.416,
    "words": [
      {
        "text": "Der",
        "start": 8.535,
        "end": 8.995
      },
      {
        "text": "absolute",
        "start": 9.055,
        "end": 10.556
      },
      {
        "text": "Supermüll!",
        "start": 10.636,
        "end": 11.416
      }
    ]
  },
  {
    "id": 4,
    "text": "Na, das freut mich ja zu hören.",
    "start": 11.496,
    "end": 13.217,
    "words": [
      {
        "text": "Na,",
        "start": 11.496,
        "end": 11.796
      },
      {
        "text": "das",
        "start": 11.836,
        "end": 12.016
      },
      {
        "text": "freut",
        "start": 12.056,
        "end": 12.296
      },
      {
        "text": "mich",
        "start": 12.316,
        "end": 12.476
      },
      {
        "text": "ja",
        "start": 12.516,
        "end": 12.677
      },
      {
        "text": "zu",
        "start": 12.697,
        "end": 12.797
      },
      {
        "text": "hören.",
        "start": 12.837,
        "end": 13.217
      }
    ]
  },
  {
    "id": 5,
    "text": "Das Schlimmste in dem Game war mit Abstand Faeria.",
    "start": 13.237,
    "end": 15.998,
    "words": [
      {
        "text": "Das",
        "start": 13.237,
        "end": 13.417
      },
      {
        "text": "Schlimmste",
        "start": 13.457,
        "end": 13.857
      },
      {
        "text": "in",
        "start": 13.897,
        "end": 13.957
      },
      {
        "text": "dem",
        "start": 13.977,
        "end": 14.177
      },
      {
        "text": "Game",
        "start": 14.197,
        "end": 14.457
      },
      {
        "text": "war",
        "start": 14.477,
        "end": 14.597
      },
      {
        "text": "mit",
        "start": 14.617,
        "end": 14.817
      },
      {
        "text": "Abstand",
        "start": 14.857,
        "end": 15.218
      },
      {
        "text": "Faeria.",
        "start": 15.258,
        "end": 15.998
      }
    ]
  },
  {
    "id": 6,
    "text": "Sie ist der wichtigste Charakter im Spiel, da kannst du dir vorstellen, was das heißt.",
    "start": 16.038,
    "end": 19.7,
    "words": [
      {
        "text": "Sie",
        "start": 16.038,
        "end": 16.138
      },
      {
        "text": "ist",
        "start": 16.158,
        "end": 16.258
      },
      {
        "text": "der",
        "start": 16.298,
        "end": 16.378
      },
      {
        "text": "wichtigste",
        "start": 16.418,
        "end": 16.798
      },
      {
        "text": "Charakter",
        "start": 16.838,
        "end": 17.198
      },
      {
        "text": "im",
        "start": 17.239,
        "end": 17.299
      },
      {
        "text": "Spiel,",
        "start": 17.339,
        "end": 17.559
      },
      {
        "text": "da",
        "start": 17.579,
        "end": 17.659
      },
      {
        "text": "kannst",
        "start": 17.679,
        "end": 17.859
      },
      {
        "text": "du",
        "start": 17.879,
        "end": 17.959
      },
      {
        "text": "dir",
        "start": 17.979,
        "end": 18.099
      },
      {
        "text": "vorstellen,",
        "start": 18.119,
        "end": 18.459
      },
      {
        "text": "was",
        "start": 18.499,
        "end": 18.599
      },
      {
        "text": "das",
        "start": 18.639,
        "end": 18.759
      },
      {
        "text": "heißt.",
        "start": 18.779,
        "end": 19.7
      }
    ]
  },
  {
    "id": 7,
    "text": "Das Writing ist so absolut beschissen, dass sie praktisch für jedes Problem in der Story verantwortlich ist und wegen ihrer KI bringt sie dauernd NPCs um.",
    "start": 19.72,
    "end": 26.383,
    "words": [
      {
        "text": "Das",
        "start": 19.72,
        "end": 19.9
      },
      {
        "text": "Writing",
        "start": 19.92,
        "end": 20.28
      },
      {
        "text": "ist",
        "start": 20.32,
        "end": 20.52
      },
      {
        "text": "so",
        "start": 20.56,
        "end": 20.76
      },
      {
        "text": "absolut",
        "start": 20.8,
        "end": 21.18
      },
      {
        "text": "beschissen,",
        "start": 21.2,
        "end": 21.6
      },
      {
        "text": "dass",
        "start": 21.62,
        "end": 21.781
      },
      {
        "text": "sie",
        "start": 21.801,
        "end": 21.881
      },
      {
        "text": "praktisch",
        "start": 21.921,
        "end": 22.241
      },
      {
        "text": "für",
        "start": 22.281,
        "end": 22.521
      },
      {
        "text": "jedes",
        "start": 22.561,
        "end": 22.821
      },
      {
        "text": "Problem",
        "start": 22.861,
        "end": 23.161
      },
      {
        "text": "in",
        "start": 23.201,
        "end": 23.281
      },
      {
        "text": "der",
        "start": 23.301,
        "end": 23.421
      },
      {
        "text": "Story",
        "start": 23.441,
        "end": 23.721
      },
      {
        "text": "verantwortlich",
        "start": 23.761,
        "end": 24.242
      },
      {
        "text": "ist",
        "start": 24.282,
        "end": 24.382
      },
      {
        "text": "und",
        "start": 24.422,
        "end": 24.502
      },
      {
        "text": "wegen",
        "start": 24.542,
        "end": 24.742
      },
      {
        "text": "ihrer",
        "start": 24.782,
        "end": 24.902
      },
      {
        "text": "KI",
        "start": 24.942,
        "end": 25.162
      },
      {
        "text": "bringt",
        "start": 25.182,
        "end": 25.382
      },
      {
        "text": "sie",
        "start": 25.422,
        "end": 25.502
      },
      {
        "text": "dauernd",
        "start": 25.522,
        "end": 25.842
      },
      {
        "text": "NPCs",
        "start": 25.862,
        "end": 26.282
      },
      {
        "text": "um.",
        "start": 26.322,
        "end": 26.383
      }
    ]
  },
  {
    "id": 8,
    "text": " So ein Mist, ich hab jemanden überfasst!",
    "start": 27.883,
    "end": 30.867,
    "words": [
      {
        "text": "So",
        "start": 27.883,
        "end": 29.005
      },
      {
        "text": "ein",
        "start": 29.065,
        "end": 29.265
      },
      {
        "text": "Mist,",
        "start": 29.305,
        "end": 29.506
      },
      {
        "text": "ich",
        "start": 29.566,
        "end": 29.666
      },
      {
        "text": "hab",
        "start": 29.686,
        "end": 29.886
      },
      {
        "text": "jemanden",
        "start": 29.906,
        "end": 30.187
      },
      {
        "text": "überfasst!",
        "start": 30.247,
        "end": 30.867
      }
    ]
  },
  {
    "id": 9,
    "text": "Was zur Hölle treibst du da?",
    "start": 30.907,
    "end": 32.97,
    "words": [
      {
        "text": "Was",
        "start": 30.907,
        "end": 31.108
      },
      {
        "text": "zur",
        "start": 31.128,
        "end": 31.228
      },
      {
        "text": "Hölle",
        "start": 31.328,
        "end": 31.628
      },
      {
        "text": "treibst",
        "start": 31.648,
        "end": 32.59
      },
      {
        "text": "du",
        "start": 32.61,
        "end": 32.73
      },
      {
        "text": "da?",
        "start": 32.75,
        "end": 32.97
      }
    ]
  },
  {
    "id": 10,
    "text": "Und jedes Mal, wenn sie Verantwortung übernehmen sollte... Wie furchtbar!",
    "start": 33.11,
    "end": 37.296,
    "words": [
      {
        "text": "Und",
        "start": 33.11,
        "end": 33.231
      },
      {
        "text": "jedes",
        "start": 33.251,
        "end": 33.511
      },
      {
        "text": "Mal,",
        "start": 33.551,
        "end": 33.711
      },
      {
        "text": "wenn",
        "start": 33.731,
        "end": 33.831
      },
      {
        "text": "sie",
        "start": 33.851,
        "end": 34.052
      },
      {
        "text": "Verantwortung",
        "start": 34.072,
        "end": 34.612
      },
      {
        "text": "übernehmen",
        "start": 34.652,
        "end": 34.993
      },
      {
        "text": "sollte...",
        "start": 35.033,
        "end": 35.754
      },
      {
        "text": "Wie",
        "start": 35.814,
        "end": 35.894
      },
      {
        "text": "furchtbar!",
        "start": 35.974,
        "end": 37.296
      }
    ]
  },
  {
    "id": 11,
    "text": "Dafür wird der Dämonen-Gott teuer bezahlen!",
    "start": 37.336,
    "end": 39.078,
    "words": [
      {
        "text": "Dafür",
        "start": 37.336,
        "end": 37.516
      },
      {
        "text": "wird",
        "start": 37.536,
        "end": 37.656
      },
      {
        "text": "der",
        "start": 37.696,
        "end": 37.817
      },
      {
        "text": "Dämonen-Gott",
        "start": 37.857,
        "end": 38.197
      },
      {
        "text": "teuer",
        "start": 38.217,
        "end": 38.457
      },
      {
        "text": "bezahlen!",
        "start": 38.477,
        "end": 39.078
      }
    ]
  },
  {
    "id": 12,
    "text": " schiebt sie die ganze verdammte Schuld einfach auf ihren verhassten Dämonengott.",
    "start": 41.707,
    "end": 45.128,
    "words": [
      {
        "text": "schiebt",
        "start": 41.707,
        "end": 41.907
      },
      {
        "text": "sie",
        "start": 41.947,
        "end": 42.047
      },
      {
        "text": "die",
        "start": 42.087,
        "end": 42.187
      },
      {
        "text": "ganze",
        "start": 42.227,
        "end": 42.487
      },
      {
        "text": "verdammte",
        "start": 42.527,
        "end": 42.908
      },
      {
        "text": "Schuld",
        "start": 42.948,
        "end": 43.288
      },
      {
        "text": "einfach",
        "start": 43.308,
        "end": 43.568
      },
      {
        "text": "auf",
        "start": 43.608,
        "end": 43.748
      },
      {
        "text": "ihren",
        "start": 43.788,
        "end": 43.968
      },
      {
        "text": "verhassten",
        "start": 44.008,
        "end": 44.368
      },
      {
        "text": "Dämonengott.",
        "start": 44.388,
        "end": 45.128
      }
    ]
  },
  {
    "id": 13,
    "text": "Der ist aber halb so wild.",
    "start": 45.168,
    "end": 46.569,
    "words": [
      {
        "text": "Der",
        "start": 45.168,
        "end": 45.329
      },
      {
        "text": "ist",
        "start": 45.369,
        "end": 45.469
      },
      {
        "text": "aber",
        "start": 45.509,
        "end": 45.689
      },
      {
        "text": "halb",
        "start": 45.709,
        "end": 45.889
      },
      {
        "text": "so",
        "start": 45.909,
        "end": 46.069
      },
      {
        "text": "wild.",
        "start": 46.109,
        "end": 46.569
      }
    ]
  },
  {
    "id": 14,
    "text": "Du bist hier das Problem!",
    "start": 46.629,
    "end": 48.25,
    "words": [
      {
        "text": "Du",
        "start": 46.629,
        "end": 46.849
      },
      {
        "text": "bist",
        "start": 46.869,
        "end": 47.009
      },
      {
        "text": "hier",
        "start": 47.049,
        "end": 47.209
      },
      {
        "text": "das",
        "start": 47.249,
        "end": 47.409
      },
      {
        "text": "Problem!",
        "start": 47.429,
        "end": 48.25
      }
    ]
  },
  {
    "id": 15,
    "text": "Sie hilft nicht im Kampf und steht dauernd im Weg, aber wehe, du versuchst auch nur, sie zu schubsen.",
    "start": 48.27,
    "end": 52.992,
    "words": [
      {
        "text": "Sie",
        "start": 48.27,
        "end": 48.37
      },
      {
        "text": "hilft",
        "start": 48.41,
        "end": 48.59
      },
      {
        "text": "nicht",
        "start": 48.61,
        "end": 48.75
      },
      {
        "text": "im",
        "start": 48.79,
        "end": 48.91
      },
      {
        "text": "Kampf",
        "start": 48.95,
        "end": 49.13
      },
      {
        "text": "und",
        "start": 49.19,
        "end": 49.29
      },
      {
        "text": "steht",
        "start": 49.31,
        "end": 49.51
      },
      {
        "text": "dauernd",
        "start": 49.55,
        "end": 49.81
      },
      {
        "text": "im",
        "start": 49.85,
        "end": 49.97
      },
      {
        "text": "Weg,",
        "start": 50.01,
        "end": 50.231
      },
      {
        "text": "aber",
        "start": 50.251,
        "end": 50.491
      },
      {
        "text": "wehe,",
        "start": 50.531,
        "end": 50.751
      },
      {
        "text": "du",
        "start": 50.791,
        "end": 50.931
      },
      {
        "text": "versuchst",
        "start": 50.971,
        "end": 51.251
      },
      {
        "text": "auch",
        "start": 51.291,
        "end": 51.431
      },
      {
        "text": "nur,",
        "start": 51.451,
        "end": 51.571
      },
      {
        "text": "sie",
        "start": 51.591,
        "end": 51.711
      },
      {
        "text": "zu",
        "start": 51.731,
        "end": 51.811
      },
      {
        "text": "schubsen.",
        "start": 51.851,
        "end": 52.992
      }
    ]
  },
  {
    "id": 16,
    "text": "Das war's!",
    "start": 53.012,
    "end": 53.672,
    "words": [
      {
        "text": "Das",
        "start": 53.012,
        "end": 53.232
      },
      {
        "text": "war's!",
        "start": 53.272,
        "end": 53.672
      }
    ]
  },
  {
    "id": 17,
    "text": "Mit einem Fiesling wie dir reise ich nicht!",
    "start": 53.692,
    "end": 57.293,
    "words": [
      {
        "text": "Mit",
        "start": 53.692,
        "end": 53.832
      },
      {
        "text": "einem",
        "start": 53.872,
        "end": 54.132
      },
      {
        "text": "Fiesling",
        "start": 54.172,
        "end": 54.552
      },
      {
        "text": "wie",
        "start": 54.572,
        "end": 54.712
      },
      {
        "text": "dir",
        "start": 54.752,
        "end": 54.993
      },
      {
        "text": "reise",
        "start": 55.033,
        "end": 55.273
      },
      {
        "text": "ich",
        "start": 55.313,
        "end": 55.453
      },
      {
        "text": "nicht!",
        "start": 55.493,
        "end": 57.293
      }
    ]
  },
  {
    "id": 18,
    "text": "Sie weigert sich, weiterzumachen!",
    "start": 57.333,
    "end": 59.194,
    "words": [
      {
        "text": "Sie",
        "start": 57.333,
        "end": 57.494
      },
      {
        "text": "weigert",
        "start": 57.534,
        "end": 57.934
      },
      {
        "text": "sich,",
        "start": 57.974,
        "end": 58.134
      },
      {
        "text": "weiterzumachen!",
        "start": 58.174,
        "end": 59.194
      }
    ]
  },
  {
    "id": 19,
    "text": "Und der letzte Autosave war ein Softlock!",
    "start": 59.234,
    "end": 61.395,
    "words": [
      {
        "text": "Und",
        "start": 59.234,
        "end": 59.394
      },
      {
        "text": "der",
        "start": 59.414,
        "end": 59.534
      },
      {
        "text": "letzte",
        "start": 59.574,
        "end": 59.855
      },
      {
        "text": "Autosave",
        "start": 59.895,
        "end": 60.395
      },
      {
        "text": "war",
        "start": 60.415,
        "end": 60.535
      },
      {
        "text": "ein",
        "start": 60.555,
        "end": 60.675
      },
      {
        "text": "Softlock!",
        "start": 60.695,
        "end": 61.395
      }
    ]
  },
  {
    "id": 20,
    "text": "Ich hab ganze drei Stunden gebraucht, um sie wieder aufzumuntern!",
    "start": 61.455,
    "end": 65.537,
    "words": [
      {
        "text": "Ich",
        "start": 61.455,
        "end": 61.535
      },
      {
        "text": "hab",
        "start": 61.555,
        "end": 61.735
      },
      {
        "text": "ganze",
        "start": 61.775,
        "end": 62.035
      },
      {
        "text": "drei",
        "start": 62.075,
        "end": 62.316
      },
      {
        "text": "Stunden",
        "start": 62.356,
        "end": 62.736
      },
      {
        "text": "gebraucht,",
        "start": 62.776,
        "end": 63.096
      },
      {
        "text": "um",
        "start": 63.136,
        "end": 63.256
      },
      {
        "text": "sie",
        "start": 63.276,
        "end": 63.396
      },
      {
        "text": "wieder",
        "start": 63.436,
        "end": 63.616
      },
      {
        "text": "aufzumuntern!",
        "start": 63.656,
        "end": 65.537
      }
    ]
  },
  {
    "id": 21,
    "text": "Allein schon daran zu denken, macht mich wieder wütend!",
    "start": 65.597,
    "end": 67.718,
    "words": [
      {
        "text": "Allein",
        "start": 65.597,
        "end": 65.857
      },
      {
        "text": "schon",
        "start": 65.877,
        "end": 66.037
      },
      {
        "text": "daran",
        "start": 66.077,
        "end": 66.337
      },
      {
        "text": "zu",
        "start": 66.357,
        "end": 66.477
      },
      {
        "text": "denken,",
        "start": 66.497,
        "end": 66.857
      },
      {
        "text": "macht",
        "start": 66.897,
        "end": 67.057
      },
      {
        "text": "mich",
        "start": 67.077,
        "end": 67.218
      },
      {
        "text": "wieder",
        "start": 67.258,
        "end": 67.418
      },
      {
        "text": "wütend!",
        "start": 67.478,
        "end": 67.718
      }
    ]
  },
  {
    "id": 22,
    "text": " Und trotzdem hast du es wieder mal bis zum Ende geschafft.",
    "start": 68.718,
    "end": 71.439,
    "words": [
      {
        "text": "Und",
        "start": 68.718,
        "end": 68.878
      },
      {
        "text": "trotzdem",
        "start": 68.898,
        "end": 69.298
      },
      {
        "text": "hast",
        "start": 69.318,
        "end": 69.539
      },
      {
        "text": "du",
        "start": 69.559,
        "end": 69.619
      },
      {
        "text": "es",
        "start": 69.639,
        "end": 69.739
      },
      {
        "text": "wieder",
        "start": 69.779,
        "end": 69.999
      },
      {
        "text": "mal",
        "start": 70.099,
        "end": 70.239
      },
      {
        "text": "bis",
        "start": 70.279,
        "end": 70.419
      },
      {
        "text": "zum",
        "start": 70.459,
        "end": 70.639
      },
      {
        "text": "Ende",
        "start": 70.679,
        "end": 70.919
      },
      {
        "text": "geschafft.",
        "start": 70.939,
        "end": 71.439
      }
    ]
  },
  {
    "id": 23,
    "text": "Und das war es auch wert, denn die drei Minuten, nachdem man den Endboss besiegt hat, bis zum Beginn der Credit behandelt das Spiel als eine Ingame-Cutscene und in der Zeit kann man Faeria endlich nach Herzenslust verprügeln.",
    "start": 71.499,
    "end": 82.564,
    "words": [
      {
        "text": "Und",
        "start": 71.499,
        "end": 71.699
      },
      {
        "text": "das",
        "start": 71.74,
        "end": 71.92
      },
      {
        "text": "war",
        "start": 71.96,
        "end": 72.16
      },
      {
        "text": "es",
        "start": 72.2,
        "end": 72.36
      },
      {
        "text": "auch",
        "start": 72.38,
        "end": 72.56
      },
      {
        "text": "wert,",
        "start": 72.6,
        "end": 72.96
      },
      {
        "text": "denn",
        "start": 73.0,
        "end": 73.16
      },
      {
        "text": "die",
        "start": 73.2,
        "end": 73.32
      },
      {
        "text": "drei",
        "start": 73.34,
        "end": 73.56
      },
      {
        "text": "Minuten,",
        "start": 73.6,
        "end": 74.001
      },
      {
        "text": "nachdem",
        "start": 74.021,
        "end": 74.301
      },
      {
        "text": "man",
        "start": 74.321,
        "end": 74.421
      },
      {
        "text": "den",
        "start": 74.461,
        "end": 74.561
      },
      {
        "text": "Endboss",
        "start": 74.601,
        "end": 74.921
      },
      {
        "text": "besiegt",
        "start": 74.961,
        "end": 75.201
      },
      {
        "text": "hat,",
        "start": 75.221,
        "end": 75.381
      },
      {
        "text": "bis",
        "start": 75.401,
        "end": 75.561
      },
      {
        "text": "zum",
        "start": 75.601,
        "end": 75.721
      },
      {
        "text": "Beginn",
        "start": 75.761,
        "end": 76.001
      },
      {
        "text": "der",
        "start": 76.021,
        "end": 76.141
      },
      {
        "text": "Credit",
        "start": 76.181,
        "end": 76.622
      },
      {
        "text": "behandelt",
        "start": 76.642,
        "end": 77.002
      },
      {
        "text": "das",
        "start": 77.042,
        "end": 77.162
      },
      {
        "text": "Spiel",
        "start": 77.182,
        "end": 77.382
      },
      {
        "text": "als",
        "start": 77.422,
        "end": 77.562
      },
      {
        "text": "eine",
        "start": 77.602,
        "end": 77.762
      },
      {
        "text": "Ingame-Cutscene",
        "start": 77.802,
        "end": 78.863
      },
      {
        "text": "und",
        "start": 78.903,
        "end": 79.043
      },
      {
        "text": "in",
        "start": 79.083,
        "end": 79.223
      },
      {
        "text": "der",
        "start": 79.243,
        "end": 79.403
      },
      {
        "text": "Zeit",
        "start": 79.423,
        "end": 79.563
      },
      {
        "text": "kann",
        "start": 79.603,
        "end": 79.723
      },
      {
        "text": "man",
        "start": 79.763,
        "end": 79.863
      },
      {
        "text": "Faeria",
        "start": 79.883,
        "end": 80.383
      },
      {
        "text": "endlich",
        "start": 80.423,
        "end": 80.724
      },
      {
        "text": "nach",
        "start": 80.764,
        "end": 80.904
      },
      {
        "text": "Herzenslust",
        "start": 80.924,
        "end": 81.544
      },
      {
        "text": "verprügeln.",
        "start": 81.584,
        "end": 82.564
      }
    ]
  },
  {
    "id": 24,
    "text": "Das ist die höllische Ironie.",
    "start": 82.584,
    "end": 84.045,
    "words": [
      {
        "text": "Das",
        "start": 82.584,
        "end": 82.764
      },
      {
        "text": "ist",
        "start": 82.824,
        "end": 82.965
      },
      {
        "text": "die",
        "start": 82.985,
        "end": 83.085
      },
      {
        "text": "höllische",
        "start": 83.125,
        "end": 83.565
      },
      {
        "text": "Ironie.",
        "start": 83.625,
        "end": 84.045
      }
    ]
  },
  {
    "id": 25,
    "text": "Je stärker dein Hass auf Faeria ist, desto entschlossener wird man es durchzuziehen, um diese drei Minuten der puren Erlösung zu erleben.",
    "start": 84.085,
    "end": 90.728,
    "words": [
      {
        "text": "Je",
        "start": 84.085,
        "end": 84.305
      },
      {
        "text": "stärker",
        "start": 84.345,
        "end": 84.705
      },
      {
        "text": "dein",
        "start": 84.725,
        "end": 84.885
      },
      {
        "text": "Hass",
        "start": 84.925,
        "end": 85.065
      },
      {
        "text": "auf",
        "start": 85.105,
        "end": 85.246
      },
      {
        "text": "Faeria",
        "start": 85.266,
        "end": 85.806
      },
      {
        "text": "ist,",
        "start": 85.846,
        "end": 85.986
      },
      {
        "text": "desto",
        "start": 86.006,
        "end": 86.346
      },
      {
        "text": "entschlossener",
        "start": 86.386,
        "end": 87.066
      },
      {
        "text": "wird",
        "start": 87.106,
        "end": 87.246
      },
      {
        "text": "man",
        "start": 87.266,
        "end": 87.406
      },
      {
        "text": "es",
        "start": 87.447,
        "end": 87.567
      },
      {
        "text": "durchzuziehen,",
        "start": 87.587,
        "end": 88.107
      },
      {
        "text": "um",
        "start": 88.167,
        "end": 88.287
      },
      {
        "text": "diese",
        "start": 88.327,
        "end": 88.547
      },
      {
        "text": "drei",
        "start": 88.567,
        "end": 88.827
      },
      {
        "text": "Minuten",
        "start": 88.867,
        "end": 89.247
      },
      {
        "text": "der",
        "start": 89.267,
        "end": 89.407
      },
      {
        "text": "puren",
        "start": 89.427,
        "end": 89.728
      },
      {
        "text": "Erlösung",
        "start": 89.768,
        "end": 90.208
      },
      {
        "text": "zu",
        "start": 90.248,
        "end": 90.348
      },
      {
        "text": "erleben.",
        "start": 90.388,
        "end": 90.728
      }
    ]
  },
  {
    "id": 26,
    "text": "Und dann, wenn es soweit ist...",
    "start": 91.268,
    "end": 93.449,
    "words": [
      {
        "text": "Und",
        "start": 91.268,
        "end": 91.488
      },
      {
        "text": "dann,",
        "start": 91.528,
        "end": 92.529
      },
      {
        "text": "wenn",
        "start": 92.549,
        "end": 92.709
      },
      {
        "text": "es",
        "start": 92.769,
        "end": 92.849
      },
      {
        "text": "soweit",
        "start": 92.889,
        "end": 93.289
      },
      {
        "text": "ist...",
        "start": 93.349,
        "end": 93.449
      }
    ]
  },
  {
    "id": 27,
    "text": " Fühlt man sich nach all dem Leid geläutert, als würde man den Sinn des Lebens begreifen.",
    "start": 95.706,
    "end": 100.438,
    "words": [
      {
        "text": "Fühlt",
        "start": 95.706,
        "end": 95.886
      },
      {
        "text": "man",
        "start": 95.906,
        "end": 96.027
      },
      {
        "text": "sich",
        "start": 96.047,
        "end": 96.247
      },
      {
        "text": "nach",
        "start": 96.287,
        "end": 96.428
      },
      {
        "text": "all",
        "start": 96.448,
        "end": 96.628
      },
      {
        "text": "dem",
        "start": 96.648,
        "end": 96.829
      },
      {
        "text": "Leid",
        "start": 96.889,
        "end": 97.129
      },
      {
        "text": "geläutert,",
        "start": 97.149,
        "end": 98.072
      },
      {
        "text": "als",
        "start": 98.132,
        "end": 98.272
      },
      {
        "text": "würde",
        "start": 98.312,
        "end": 98.573
      },
      {
        "text": "man",
        "start": 98.593,
        "end": 98.733
      },
      {
        "text": "den",
        "start": 98.773,
        "end": 98.934
      },
      {
        "text": "Sinn",
        "start": 98.974,
        "end": 99.215
      },
      {
        "text": "des",
        "start": 99.235,
        "end": 99.415
      },
      {
        "text": "Lebens",
        "start": 99.455,
        "end": 99.796
      },
      {
        "text": "begreifen.",
        "start": 99.816,
        "end": 100.438
      }
    ]
  },
  {
    "id": 28,
    "text": "Hauptsache du hattest ein Spaß.",
    "start": 100.478,
    "end": 101.982,
    "words": [
      {
        "text": "Hauptsache",
        "start": 100.478,
        "end": 100.939
      },
      {
        "text": "du",
        "start": 100.979,
        "end": 101.099
      },
      {
        "text": "hattest",
        "start": 101.139,
        "end": 101.46
      },
      {
        "text": "ein",
        "start": 101.52,
        "end": 101.661
      },
      {
        "text": "Spaß.",
        "start": 101.701,
        "end": 101.982
      }
    ]
  }
]